kmers/__init__.py
kmers/kmers.py
kmers-0.2.1.dist-info/DESCRIPTION.rst
kmers-0.2.1.dist-info/METADATA
kmers-0.2.1.dist-info/RECORD
kmers-0.2.1.dist-info/WHEEL
kmers-0.2.1.dist-info/metadata.json
kmers-0.2.1.dist-info/top_level.txt
